fastapi_cloud_drives/__init__.py
fastapi_cloud_drives/config.py
fastapi_cloud_drives/fastapi_google.py
fastapi_cloud_drives-0.1.4.dist-info/WHEEL
fastapi_cloud_drives-0.1.4.dist-info/METADATA
fastapi_cloud_drives-0.1.4.dist-info/RECORD
