Metadata-Version: 2.1
Name: fastapi-cloud-drives
Version: 0.1.4
Summary: Module for FastAPI to work with cloud drives
Home-page: https://github.com/MadeByMads/fastapi-cloud-drives
License: MIT
Keywords: FastAPI,Google Drive,OneDrive,Dropbox,Amazon S3
Author: Hasan Aliyev
Author-email: hasan.aliyev.555@gmail.com
Requires-Python: >=3.6,<4.0
Classifier: License :: OSI Approved :: MIT License
Classifier: Programming Language :: Python :: 3
Classifier: Programming Language :: Python :: 3.6
Classifier: Programming Language :: Python :: 3.7
Classifier: Programming Language :: Python :: 3.8
Classifier: Programming Language :: Python :: 3.9
Classifier: Topic :: Software Development :: Libraries :: Python Modules
Requires-Dist: fastapi (>=0.63.0,<0.64.0)
Requires-Dist: google-api-python-client (>=1.12.8,<2.0.0)
Requires-Dist: google-auth-oauthlib (>=0.4.2,<0.5.0)
Requires-Dist: oauth2client (>=4.1.3,<5.0.0)
Requires-Dist: pydantic (>=1.7.3,<2.0.0)
Requires-Dist: uvicorn (>=0.13.3,<0.14.0)
Project-URL: Bug Tracker, https://github.com/MadeByMads/fastapi-cloud-drives/issues
Project-URL: Repository, https://github.com/MadeByMads/fastapi-cloud-drives
